reproducible_block.py
torch_reproducible_block-0.0.1.dist-info/LICENSE
torch_reproducible_block-0.0.1.dist-info/METADATA
torch_reproducible_block-0.0.1.dist-info/WHEEL
torch_reproducible_block-0.0.1.dist-info/top_level.txt
torch_reproducible_block-0.0.1.dist-info/RECORD
