Metadata-Version: 2.1
Name: torch-reproducible-block
Version: 0.0.1
Summary: Control random number generator state via reproducible blocks
Home-page: https://github.com/j3rome/torch-reproducible-block
Author: Jerome Abdelnour
License: UNKNOWN
Platform: UNKNOWN
Classifier: Programming Language :: Python :: 3
Classifier: License :: OSI Approved :: GNU General Public License v3 (GPLv3)
Classifier: Operating System :: OS Independent
Requires-Python: >=3.6
License-File: LICENSE
Requires-Dist: numpy
Requires-Dist: torch
